odoo8_addon_pos_order_pricelist_change-8.0.1.0.0-py2.7-nspkg.pth
odoo_addons/pos_order_pricelist_change/__openerp__.py
odoo_addons/pos_order_pricelist_change/__init__.py
odoo_addons/pos_order_pricelist_change/README.rst
odoo_addons/pos_order_pricelist_change/models/__init__.py
odoo_addons/pos_order_pricelist_change/models/pos_order.py
odoo_addons/pos_order_pricelist_change/i18n/nl_NL.po
odoo_addons/pos_order_pricelist_change/i18n/pos_order_pricelist_change.pot
odoo_addons/pos_order_pricelist_change/i18n/it.po
odoo_addons/pos_order_pricelist_change/i18n/es.po
odoo_addons/pos_order_pricelist_change/i18n/sl.po
odoo_addons/pos_order_pricelist_change/i18n/fr.po
odoo_addons/pos_order_pricelist_change/views/view.xml
odoo_addons/pos_order_pricelist_change/tests/test_pos_order_pricelist_change.py
odoo_addons/pos_order_pricelist_change/tests/__init__.py
odoo_addons/pos_order_pricelist_change/demo/demo.xml
odoo_addons/pos_order_pricelist_change/demo/res_groups.yml
odoo_addons/pos_order_pricelist_change/static/description/icon.png
odoo_addons/pos_order_pricelist_change/static/src/img/screenshot_warning.png
odoo8_addon_pos_order_pricelist_change-8.0.1.0.0.dist-info/top_level.txt
odoo8_addon_pos_order_pricelist_change-8.0.1.0.0.dist-info/WHEEL
odoo8_addon_pos_order_pricelist_change-8.0.1.0.0.dist-info/RECORD
odoo8_addon_pos_order_pricelist_change-8.0.1.0.0.dist-info/metadata.json
odoo8_addon_pos_order_pricelist_change-8.0.1.0.0.dist-info/DESCRIPTION.rst
odoo8_addon_pos_order_pricelist_change-8.0.1.0.0.dist-info/METADATA
odoo8_addon_pos_order_pricelist_change-8.0.1.0.0.dist-info/namespace_packages.txt
