Metadata-Version: 2.0
Name: odoo8-addon-pos-order-pricelist-change
Version: 8.0.1.0.0
Summary: Improve pricelist changes for POS Order in back office
Home-page: http://www.grap.coop
Author: UNKNOWN
Author-email: UNKNOWN
License: AGPL-3
Platform: UNKNOWN
Requires-Dist: odoo (<9.0a,>=8.0a)
Classifier: Programming Language :: Python :: 2.7
Classifier: Framework :: Odoo
Classifier: License :: OSI Approved :: GNU Affero General Public License v3
